notion2hugo/__init__.py
notion2hugo/__main__.py
notion2hugo/base.py
notion2hugo/exporter.py
notion2hugo/formatter.py
notion2hugo/provider.py
notion2hugo/registry.py
notion2hugo/runner.py
notion2hugo/utils.py
notion2hugo-0.2.0.dist-info/LICENSE
notion2hugo-0.2.0.dist-info/METADATA
notion2hugo-0.2.0.dist-info/WHEEL
notion2hugo-0.2.0.dist-info/entry_points.txt
notion2hugo-0.2.0.dist-info/top_level.txt
notion2hugo-0.2.0.dist-info/RECORD
