Metadata-Version: 2.1
Name: notion2hugo
Version: 0.2.0
Summary: Converts Notion documents into Markdown format files compatbile with the Hugo framework.
Author-email: Chintak Sheth <chintaksheth@gmail.com>
License: MIT License
Project-URL: Homepage, https://github.com/chintak/notion2hugo
Keywords: notion,hugo,markdown
Classifier: Programming Language :: Python :: 3.9
Classifier: Programming Language :: Python :: 3.10
Classifier: Programming Language :: Python :: 3.11
Classifier: Development Status :: 4 - Beta
Classifier: License :: OSI Approved :: MIT License
Requires-Python: <4,>=3.9
License-File: LICENSE
Requires-Dist: notion-client ==2.0.0
Requires-Dist: requests ==2.31.0
Requires-Dist: pytest
Requires-Dist: pytest-asyncio
Provides-Extra: dev
Requires-Dist: black ; extra == 'dev'
Requires-Dist: bumpver ; extra == 'dev'
Requires-Dist: build ; extra == 'dev'
Requires-Dist: twine ; extra == 'dev'
Requires-Dist: isort ; extra == 'dev'
Requires-Dist: pip-tools ; extra == 'dev'
Requires-Dist: types-requests ; extra == 'dev'
